pywatch/__init__.py
pywatch/__main__.py
pywatch/parse_setup.py
pywatch/dist/index.html
pywatch/dist/assets/detector.blend
pywatch/dist/assets/detector.glb
pywatch/dist/assets/index-CeWDZzsQ.js
pywatch/dist/assets/index-Cx65kQ0t.css
pywatch/dist/assets/index-DbyDGBtc.js
pywatch/dist/assets/index-DbyDGBtc.js.map
pywatch/dist/assets/index-OAbvmCsy.css
pywatch/dist/assets/index-dwDn0vI4.js
pywatch/readout/__init__.py
pywatch/readout/detector.py
pywatch/readout/detector_pool.py
pywatch/readout/event_data_collection.py
pywatch/readout/hit_data.py
pywatch/readout/measurement.py
pywatch/readout/pool_thread.py
pywatch/readout/port_access.py
pywatch/readout/py.typed
pywatch/server/__init__.py
pywatch/server/color.py
pywatch/server/main.py
pywatch/server/simulation.py
pywatch/server/detector_logic_calculation/__init__.py
pywatch/server/detector_logic_calculation/coincidences.py
pywatch/server/detector_logic_calculation/detector.py
pywatch/server/detector_logic_calculation/vector.py
pywatch_tracker-0.3.1.dist-info/METADATA
pywatch_tracker-0.3.1.dist-info/WHEEL
pywatch_tracker-0.3.1.dist-info/top_level.txt
pywatch_tracker-0.3.1.dist-info/RECORD
