Metadata-Version: 2.1
Name: pywatch-tracker
Version: 0.3.1
Summary: Coincidence Measurements with CosmicWatch detectors.
Home-page: https://gitlab.uni-bonn.de/s6garemi/tracker_webapp
Author: Gabriel Remiszewski
Requires-Dist: eventlet~=0.36.1
Requires-Dist: quart>=0.18.4
Requires-Dist: pyserial>=3.5
Requires-Dist: pyserial-asyncio>=0.6
Requires-Dist: typing-extensions
Requires-Dist: numpy>=1.24.4
Requires-Dist: pandas>=2.0.3
Requires-Dist: colour>=0.1.5
